fsociety/__init__.py
fsociety/__main__.py
fsociety/__version__.py
fsociety/console.py
fsociety/core/__init__.py
fsociety/core/config.py
fsociety/core/hosts.py
fsociety/core/menu.py
fsociety/core/repo.py
fsociety/core/usernames.py
fsociety/core/utilities.py
fsociety/information_gathering/__init__.py
fsociety/information_gathering/cli.py
fsociety/information_gathering/gitgraber.py
fsociety/information_gathering/hydrarecon.py
fsociety/information_gathering/s3scanner.py
fsociety/information_gathering/sherlock.py
fsociety/information_gathering/sqlmap.py
fsociety/information_gathering/striker.py
fsociety/information_gathering/sublist3r.py
fsociety/networking/__init__.py
fsociety/networking/bettercap.py
fsociety/networking/cli.py
fsociety/networking/nmap.py
fsociety/obfuscation/__init__.py
fsociety/obfuscation/cli.py
fsociety/obfuscation/cuteit.py
fsociety/passwords/__init__.py
fsociety/passwords/changeme.py
fsociety/passwords/cli.py
fsociety/passwords/cr3dov3r.py
fsociety/passwords/cupp.py
fsociety/passwords/hash_buster.py
fsociety/passwords/traitor.py
fsociety/web_apps/__init__.py
fsociety/web_apps/cli.py
fsociety/web_apps/photon.py
fsociety/web_apps/xsstrike.py
fsociety-3.2.9.dist-info/LICENSE
fsociety-3.2.9.dist-info/METADATA
fsociety-3.2.9.dist-info/WHEEL
fsociety-3.2.9.dist-info/entry_points.txt
fsociety-3.2.9.dist-info/top_level.txt
fsociety-3.2.9.dist-info/RECORD
