Metadata-Version: 2.1
Name: fsociety
Version: 3.2.9
Summary: A Modular Penetration Testing Framework
Home-page: https://fsociety.dev/
Author: fsociety-team
Author-email: contact@fsociety.dev
License: MIT
Project-URL: Packages, https://github.com/fsociety-team/fsociety/blob/main/PACKAGES.md
Project-URL: Changelog, https://github.com/fsociety-team/fsociety/blob/main/CHANGELOG.md
Project-URL: Funding, https://github.com/sponsors/thehappydinoa
Project-URL: Tracker, https://github.com/fsociety-team/fsociety/issues
Project-URL: Source, https://github.com/fsociety-team/fsociety
Keywords: fsociety
Platform: UNKNOWN
Classifier: Topic :: Internet
Classifier: Topic :: Security
Classifier: Framework :: Flake8
Classifier: Environment :: Console
Classifier: Natural Language :: English
Classifier: Operating System :: OS Independent
Classifier: License :: OSI Approved :: MIT License
Classifier: Programming Language :: Python
Classifier: Programming Language :: Python :: 3 :: Only
Classifier: Programming Language :: Python :: 3
Classifier: Programming Language :: Python :: 3.7
Classifier: Programming Language :: Python :: 3.8
Classifier: Programming Language :: Python :: 3.9
Classifier: Programming Language :: Python :: 3.10
Classifier: Programming Language :: Python :: 3.11
Classifier: Programming Language :: Python :: Implementation :: PyPy
Requires-Python: >=3.7.0
Requires-Dist: distro (>=1.7.0)
Requires-Dist: GitPython (>=3.1.3)
Requires-Dist: requests (>=2.23.0)
Requires-Dist: rich (>=9.2.0)
Provides-Extra: dev
Requires-Dist: black (==23.3.0) ; extra == 'dev'
Requires-Dist: flake8 (==6.0.0) ; extra == 'dev'
Requires-Dist: flake8-black (==0.3.6) ; extra == 'dev'
Requires-Dist: flake8-comprehensions (==3.13.0) ; extra == 'dev'
Requires-Dist: flake8-simplify (==0.20.0) ; extra == 'dev'
Requires-Dist: isort (==5.12.0) ; extra == 'dev'
Requires-Dist: mypy (==1.3.0) ; extra == 'dev'
Requires-Dist: pre-commit (==3.3.3) ; extra == 'dev'
Requires-Dist: twine (==4.0.2) ; extra == 'dev'
